Metadata-Version: 2.1
Name: Cip-library
Version: 0.3
Summary: This is a test project
Home-page: https://cip_library.com
Author: Cip
Author-email: Cip@gmail.com
License: UNKNOWN
Platform: UNKNOWN
Requires-Python: >=3.10
